jupyterlab_crosscompute/__init__.py
jupyterlab_crosscompute/_version.py
jupyterlab_crosscompute/constants.py
jupyterlab_crosscompute/handlers.py
jupyterlab_crosscompute/macros.py
jupyterlab_crosscompute/routines.py
jupyterlab_crosscompute/labextension/package.json
jupyterlab_crosscompute/labextension/schemas/jupyterlab-crosscompute/package.json.orig
jupyterlab_crosscompute/labextension/schemas/jupyterlab-crosscompute/plugin.json
jupyterlab_crosscompute/labextension/static/728.77f5b4128f91b9af2535.js
jupyterlab_crosscompute/labextension/static/862.c48f1d7986f3e0fec005.js
jupyterlab_crosscompute/labextension/static/remoteEntry.4751efed38c1ea0d8186.js
jupyterlab_crosscompute/labextension/static/style.js
jupyterlab_crosscompute/labextension/static/third-party-licenses.json
jupyterlab_crosscompute-0.2.4.1.data/data/etc/jupyter/jupyter_notebook_config.d/jupyterlab_crosscompute.json
jupyterlab_crosscompute-0.2.4.1.data/data/etc/jupyter/jupyter_server_config.d/jupyterlab_crosscompute.json
jupyterlab_crosscompute-0.2.4.1.data/data/share/jupyter/labextensions/jupyterlab-crosscompute/install.json
jupyterlab_crosscompute-0.2.4.1.data/data/share/jupyter/labextensions/jupyterlab-crosscompute/package.json
jupyterlab_crosscompute-0.2.4.1.data/data/share/jupyter/labextensions/jupyterlab-crosscompute/schemas/jupyterlab-crosscompute/package.json.orig
jupyterlab_crosscompute-0.2.4.1.data/data/share/jupyter/labextensions/jupyterlab-crosscompute/schemas/jupyterlab-crosscompute/plugin.json
jupyterlab_crosscompute-0.2.4.1.data/data/share/jupyter/labextensions/jupyterlab-crosscompute/static/728.77f5b4128f91b9af2535.js
jupyterlab_crosscompute-0.2.4.1.data/data/share/jupyter/labextensions/jupyterlab-crosscompute/static/862.c48f1d7986f3e0fec005.js
jupyterlab_crosscompute-0.2.4.1.data/data/share/jupyter/labextensions/jupyterlab-crosscompute/static/remoteEntry.4751efed38c1ea0d8186.js
jupyterlab_crosscompute-0.2.4.1.data/data/share/jupyter/labextensions/jupyterlab-crosscompute/static/style.js
jupyterlab_crosscompute-0.2.4.1.dist-info/LICENSE
jupyterlab_crosscompute-0.2.4.1.dist-info/METADATA
jupyterlab_crosscompute-0.2.4.1.dist-info/WHEEL
jupyterlab_crosscompute-0.2.4.1.dist-info/top_level.txt
jupyterlab_crosscompute-0.2.4.1.dist-info/RECORD
