Metadata-Version: 2.1
Name: jupyterlab-crosscompute
Version: 0.2.4.1
Summary: CrossCompute Extensions for JupyterLab
Home-page: https://github.com/crosscompute/jupyterlab-crosscompute
Author: CrossCompute Inc.
Author-email: support@crosscompute.com
License: BSD-3-Clause
Keywords: Jupyter,JupyterLab,JupyterLab3
Platform: Linux
Platform: Mac OS X
Platform: Windows
Classifier: License :: OSI Approved :: BSD License
Classifier: Programming Language :: Python
Classifier: Programming Language :: Python :: 3
Classifier: Programming Language :: Python :: 3.10
Classifier: Framework :: Jupyter
Classifier: Framework :: Jupyter :: JupyterLab
Classifier: Framework :: Jupyter :: JupyterLab :: 3
Classifier: Framework :: Jupyter :: JupyterLab :: Extensions
Classifier: Framework :: Jupyter :: JupyterLab :: Extensions :: Prebuilt
Requires-Python: >=3.7
License-File: LICENSE
Requires-Dist: crosscompute >=0.9.4
Requires-Dist: invisibleroads-macros-disk >=1.3.0
Requires-Dist: invisibleroads-macros-security >=1.0.3
Requires-Dist: invisibleroads-macros-web >=0.3.0
Requires-Dist: jupyter-server >=2.0
